i2c_24xx256_EEPROM_design.v
module i2c_EEPROM (
    input clk, reset, newd, page_wrt,
    input [2:0] a_n,
    input read,
    input [5:0] no_of_bytes,
    output sda,
    output scl,
    input [7:0] din,
    input [15:0] addr,
    output [7:0] dout,
    output reg busy, ack_err, done
);

    parameter sys_freq = 40000000; //40MHZ
    parameter i2c_freq = 100000; //100KHz

    parameter clk_count4 = (sys_freq/i2c_freq); // 400
    parameter clk_count = (clk_count4)/4; // 100

    integer count = 0; // for slow clk
    reg [1:0] pulse = 0; // segmentation of 1 bit duration

    // COUNT LOGIC
    always @(posedge clk) begin
        if (reset) count <= 0;
        else begin
            if (busy == 0) count <= 0;
            else begin
                if (count == clk_count - 1) count <= 0;
                else count <= count + 1;
            end
        end
    end

    // PULSE LOGIC
    always @(posedge clk) begin
        if (reset) pulse <= 0;
        else begin
            if (busy == 0) pulse <= 0;
            else begin
                if (count == clk_count - 1) begin
                    if (pulse == 3) pulse <= 0;
                    else pulse <= pulse + 1;
                end
                else pulse <= pulse;
            end
        end
    end
    
    parameter IDLE = 0, START = 1, WRITE_CTRL = 2, ACK_1 = 3, WRITE_DATA = 4,
                READ_DATA = 5, ACK_2 = 6, MASTER_ACK = 7, STOP = 8, WRITE_ADDR_H = 9,
                WRITE_ADDR_L = 10, ACK_3 = 11, ACK_4 = 12, ACK_5 = 13, PAGE_WRITE = 14; 

    reg [4:0] state;
    reg scl_t = 0;
    reg sda_t = 0;

    reg [3:0] bit_count = 0;
    integer p_count = 0;
    reg [7:0] data_ctrl = 0, data_tx = 0;
    reg [7:0] data_addr_h, data_addr_l;
    reg r_ack;
    reg [7:0] rx_data;
    reg [7:0] page_data [62:0];
    reg sda_en;

    always @(posedge clk) begin
        if (reset) begin
            bit_count <= 0;
            data_ctrl <= 0;
            data_tx <= 0;
            scl_t <= 1;
            sda_t <= 1;
            busy <= 0;
            ack_err <= 0;
            done <= 0;
            state <= IDLE;
        end
        else begin
            case (state)
                IDLE : begin
                    done <= 0;
                    if (newd) begin
                        state <= START;
                        data_ctrl <= {4'b1010, a_n, read};
                        data_addr_h <= addr[15:8];
                        data_addr_l <= addr[7:0];
                        data_tx <= din;
                        busy <= 1;
                        ack_err <= 0;
                    end
                    else begin
                        state <= IDLE;
                        data_ctrl <= 0;
                        data_tx <= 0;
                        busy <= 0;
                        ack_err <= 0;
                    end
                end

                //////////////////////////////////////

                START : begin
                    sda_en <= 1; 
                    case (pulse)
                        0 : begin scl_t = 1; sda_t = 1; end
                        1 : begin scl_t = 1; sda_t = 1; end
                        2 : begin scl_t = 1; sda_t = 0; end
                        3 : begin scl_t = 1; sda_t = 0; end
                    endcase

                    state <= (count == clk_count - 1 & pulse == 3) ? WRITE_CTRL : START; // possible bug
                end

                //////////////////////////////////////

                WRITE_CTRL : begin
                    sda_en <= 1;
                    if (bit_count <= 7) begin
                        case (pulse)
                            0 : begin scl_t = 0; sda_t = 0; end
                            1 : begin scl_t = 0; sda_t = data_ctrl[7-bit_count]; end
                            2 : begin scl_t = 1; end
                            3 : begin scl_t = 1; end
                        endcase

                        if (count == clk_count - 1 & pulse == 3) begin
                            state <= WRITE_CTRL;
                            bit_count <= bit_count + 1;
                            scl_t <= 0;
                        end
                        else begin
                            state <= WRITE_CTRL;
                            bit_count <= bit_count;
                        end
                    end

                    else begin
                        state <= ACK_1;
                        scl_t <= 0;
                        sda_en <= 0;
                        bit_count <= 0;
                    end
                end

                //////////////////////////////////////

                ACK_1 : begin
                    sda_en <= 0;
                    case (pulse)
                        0 : begin scl_t <= 0; sda_t <= 0; end
                        1 : begin scl_t <= 0; sda_t <= 0; end // 0 ack coz no slave rn
                        2 : begin scl_t <= 1; sda_t <= 0; r_ack <= 0; end // change logic, when slave avl
                        3 : begin scl_t <= 1; sda_t <= 0; end
                    endcase

                    if (count == clk_count - 1 & pulse == 3) begin
                        if (r_ack == 0) begin
                            state <= WRITE_ADDR_H;
                            sda_en <= 1;
                            sda_t <= 1;
                            ack_err <= 0;
                        end
                        else begin
                            state <= STOP;
                            sda_en <= 1;
                            ack_err <= 1;
                        end
                    end
                    else begin
                        state <= ACK_1;
                    end
                end

                //////////////////////////////////////

                WRITE_ADDR_H : begin
                    sda_en <= 1;
                    if (bit_count <= 7) begin
                        case (pulse)
                            0 : begin scl_t = 0; sda_t = 0; end
                            1 : begin scl_t = 0; sda_t = data_addr_h[7-bit_count]; end
                            2 : begin scl_t = 1; end
                            3 : begin scl_t = 1; end
                        endcase

                        if (count == clk_count - 1 & pulse == 3) begin
                            state <= WRITE_ADDR_H;
                            bit_count <= bit_count + 1;
                            scl_t <= 0;
                        end
                        else begin
                            state <= WRITE_ADDR_H;
                            bit_count <= bit_count;
                        end
                    end

                    else begin
                        state <= ACK_3;
                        scl_t <= 0;
                        sda_en <= 0;
                        bit_count <= 0;
                    end
                end

                //////////////////////////////////////

                ACK_3 : begin
                    sda_en <= 0;
                    case (pulse)
                        0 : begin scl_t <= 0; sda_t <= 0; end
                        1 : begin scl_t <= 0; sda_t <= 0; end // 0 ack coz no slave rn
                        2 : begin scl_t <= 1; sda_t <= 0; r_ack <= 0; end // change logic, when slave avl
                        3 : begin scl_t <= 1; sda_t <= 0; end
                    endcase

                    if (count == clk_count - 1 & pulse == 3) begin
                        if (r_ack == 0) begin
                            state <= WRITE_ADDR_L;
                            sda_en <= 1;
                            sda_t <= 1;
                            ack_err <= 0;
                        end
                        else begin
                            state <= STOP;
                            sda_en <= 1;
                            ack_err <= 1;
                        end
                    end
                    else begin
                        state <= ACK_3;
                    end
                end

                //////////////////////////////////////

                WRITE_ADDR_L : begin
                    sda_en <= 1;
                    if (bit_count <= 7) begin
                        case (pulse)
                            0 : begin scl_t = 0; sda_t = 0; end
                            1 : begin scl_t = 0; sda_t = data_addr_l[7-bit_count]; end
                            2 : begin scl_t = 1; end
                            3 : begin scl_t = 1; end
                        endcase

                        if (count == clk_count - 1 & pulse == 3) begin
                            state <= WRITE_ADDR_L;
                            bit_count <= bit_count + 1;
                            scl_t <= 0;
                        end
                        else begin
                            state <= WRITE_ADDR_L;
                            bit_count <= bit_count;
                        end
                    end

                    else begin
                        state <= ACK_4;
                        scl_t <= 0;
                        sda_en <= 0;
                        bit_count <= 0;
                    end
                end

                //////////////////////////////////////

                ACK_4 : begin
                    sda_en <= 0;
                    case (pulse)
                        0 : begin scl_t <= 0; sda_t <= 0; end
                        1 : begin scl_t <= 0; sda_t <= 0; end // 0 ack coz no slave rn
                        2 : begin scl_t <= 1; sda_t <= 0; r_ack <= 0; end // change logic, when slave avl
                        3 : begin scl_t <= 1; sda_t <= 0; end
                    endcase

                    if (count == clk_count - 1 & pulse == 3) begin
                        if (r_ack == 0 & data_ctrl[0] == 0) begin
                            state <= WRITE_DATA;
                            sda_en <= 1;
                            sda_t <= 0;
                        end
                        else if (r_ack == 0 & data_ctrl[0] == 1) begin
                            state <= READ_DATA;
                            sda_en <= 0;
                            sda_t <= 1;
                        end
                        else begin
                            state <= STOP;
                            sda_en <= 1;
                            ack_err <= 1;
                        end
                    end
                    else begin
                        state <= ACK_4;
                    end
                end

                //////////////////////////////////////

                WRITE_DATA : begin
                    if (bit_count <= 7) begin
                        
                        sda_en <= 1;
                        case (pulse)
                            0 : begin scl_t <= 0; sda_t <= 0; end
                            1 : begin scl_t <= 0; sda_t <= data_tx[7-bit_count]; end
                            2 : begin scl_t <= 1; end
                            3 : begin scl_t <= 1; end
                        endcase

                        if (count == clk_count - 1 & pulse == 3) begin
                            state <= WRITE_DATA;
                            bit_count <= bit_count + 1;
                            scl_t <= 0;
                        end
                        else begin
                            state <= WRITE_DATA;
                            bit_count <= bit_count;
                        end
                    end
                    else begin
                        state <= ACK_2;
                        sda_en <= 0;
                        scl_t <= 0;
                        bit_count <= 0; 
                    end
                end

                //////////////////////////////////////

                READ_DATA : begin
                    sda_en <= 0;
                    if (bit_count <= 7) begin
                        case (pulse)
                            0 : begin scl_t <= 0; sda_t <= 0; end
                            1 : begin scl_t <= 0; end
                            2 : begin 
                                scl_t <= 1; 
                                // rx_data <= (pulse == 2 & count == 0) ? {rx_data[6:0],sda} : rx_data;
                            end
                            3 : begin scl_t <= 1; end
                        endcase

                        if (count == clk_count - 1 & pulse == 3) begin
                            bit_count <= bit_count + 1;
                            state <= READ_DATA;
                            scl_t <= 0;
                        end
                        else begin
                            state <= READ_DATA;
                            bit_count <= bit_count;
                        end
                    end
                    else begin
                        bit_count <= 0;
                        sda_en <= 1;
                        state <= MASTER_ACK;
                    end
                end

                //////////////////////////////////////

                MASTER_ACK : begin
                    sda_en <= 1;
                    case (pulse)
                        0 : begin scl_t <= 0; sda_t <= 1; end // possible bug
                        1 : begin scl_t <= 0; sda_t <= 1; end 
                        2 : begin scl_t <= 1; sda_t <= 1; end
                        3 : begin scl_t <= 1; sda_t <= 1; end  
                    endcase

                    if (count == clk_count - 1 & pulse == 3) begin
                        state <= STOP;
                        sda_t <= 0;
                        sda_en <= 1;    
                    end
                    else begin
                        state <= MASTER_ACK;
                    end
                end

                //////////////////////////////////////

                ACK_2 : begin
                    sda_en <= 0;
                    case (pulse)
                        0 : begin scl_t <= 0; sda_t <= 0; end
                        1 : begin scl_t <= 0; sda_t <= 0; end
                        2 : begin scl_t <= 1; sda_t <= 0; r_ack <= 0; end
                        3 : begin scl_t <= 1; end 
                    endcase

                    if (count == clk_count - 1 & pulse == 3) begin // possibel bug
                        if (r_ack == 0 && page_wrt == 1) begin
                            state <= PAGE_WRITE;
                            ack_err <= 0;
                            sda_en <= 1;
                            sda_t <= 0;
                        end
                        else if (r_ack == 0 && page_wrt == 0) begin
                            state <= STOP;
                            ack_err <= 0;
                            sda_en <= 1;
                            sda_t <= 0;
                        end
                        else begin
                            state <= STOP;
                            ack_err <= 1;
                        end
                    end
                    else begin
                        state <= ACK_2;
                    end
                end

                //////////////////////////////////////

                PAGE_WRITE : begin
                    if (p_count <= no_of_bytes - 1) begin
                        sda_en <= 1;
                        if (bit_count <= 7) begin
                            case (pulse)
                                0 : begin scl_t <= 0; sda_t <= 0; end
                                1 : begin scl_t <= 0; sda_t <= page_data[p_count][7-bit_count]; end
                                2 : begin scl_t <= 1; end
                                3 : begin scl_t <= 1; end
                            endcase

                            if (count == clk_count - 1 & pulse == 3) begin
                                state <= PAGE_WRITE;
                                bit_count <= bit_count + 1;
                                scl_t <= 0;
                            end
                            else begin
                                state <= PAGE_WRITE;
                                bit_count <= bit_count;
                            end
                        end
                        else begin
                            state <= PAGE_WRITE;
                            sda_en <= 1;
                            scl_t <= 0;
                            bit_count <= 0; 
                            p_count <= p_count + 1;
                        end
                    end

                    else begin
                        state <= ACK_5;
                        count <= 0;
                        bit_count <= 0;
                        sda_en <= 0;
                        sda_t <= 0;
                    end
                end

                //////////////////////////////////////

                ACK_5 : begin
                    sda_en <= 0;
                    case (pulse)
                        0 : begin scl_t <= 0; sda_t <= 0; end
                        1 : begin scl_t <= 0; sda_t <= 0; end // 0 ack coz no slave rn
                        2 : begin scl_t <= 1; sda_t <= 0; r_ack <= 0; end // change logic, when slave avl
                        3 : begin scl_t <= 1; sda_t <= 0; end
                    endcase

                    if (count == clk_count - 1 & pulse == 3) begin
                        if (r_ack == 0) begin
                            state <= STOP;
                            sda_en <= 1;
                            sda_t <= 1;
                            ack_err <= 0;
                        end
                        else begin
                            state <= STOP;
                            sda_en <= 1;
                            ack_err <= 1;
                        end
                    end
                    else begin
                        state <= ACK_5;
                    end
                end

                //////////////////////////////////////

                STOP : begin
                    sda_en <= 1;
                    case (pulse)
                        0 : begin scl_t <= 1; sda_t <= 0; end
                        1 : begin scl_t <= 1; sda_t <= 0; end
                        2 : begin scl_t <= 1; sda_t <= 1; end
                        3 : begin scl_t <= 1; sda_t <= 1; end
                    endcase

                    if (count == clk_count -1 & pulse == 3) begin
                        state <= IDLE;
                        scl_t <= 0;
                        sda_en <= 1;
                        busy <= 0;
                        done <= 1; // done is only high here
                    end
                    else begin
                        state <= STOP;
                    end
                end

                //////////////////////////////////////

                default: state <= IDLE;
            endcase
        end
    end  

    assign sda = (sda_en == 1) ? sda_t : 1'bz;
    assign scl = scl_t;
    assign dout = rx_data;
endmodule

module tb;
    reg clk =0; 
    reg rst = 0;
    reg newd = 0;
    reg [15:0] addr = 0;
    reg [2:0] a_n = 0;
    reg read = 0;
    reg page_wrt = 0;
    reg [7:0] din = 0;
    reg [5:0] no_of_bytes = 0;
    wire [7:0] dout;
    wire sda,scl;
    wire busy;
    wire ack_err;
    wire done;
    integer i;   
    integer j; 

    i2c_EEPROM dut (clk, rst, newd, page_wrt, a_n, read, no_of_bytes,
                    sda, scl, din, addr, dout, busy, ack_err, done);

    always #5 clk = ~clk;
    
    initial begin
        rst = 1;
        repeat(5) @(posedge clk);
        rst = 0;
        newd = 1;
        read = 0;
        a_n = 3'b101;
        page_wrt = 1;
        addr = 16'hABCD;
        din = 8'b10101010;
        no_of_bytes = 5;
        @(negedge busy);
        repeat(5) @(posedge clk);
        $finish;
    end


    initial begin
        for (i = 0; i < 63; i = i + 1) begin
           dut.page_data[i] = 8'h00;
        end
        #10;
        for (j = 0; j < 5; j++) begin
            dut.page_data[j] = 8'hAA;
        end
    end

    initial begin
        $dumpfile("dump.vcd");
        $dumpvars;
    end

    initial begin
        #10000000;
        $display("----------------------");
        $display("INFINITE LOOP DETECTED");
        $display("----------------------");
        $finish;
    end
endmodule

12c_24xx256_EEPROM.vcd
$date
	Sun May 24 06:29:43 2026
$end
$version
	Icarus Verilog
$end
$timescale
	1s
$end
$scope module tb $end
$var wire 1 ! sda $end
$var wire 1 " scl $end
$var wire 8 # dout [7:0] $end
$var wire 1 $ done $end
$var wire 1 % busy $end
$var wire 1 & ack_err $end
$var reg 3 ' a_n [2:0] $end
$var reg 16 ( addr [15:0] $end
$var reg 1 ) clk $end
$var reg 8 * din [7:0] $end
$var reg 1 + newd $end
$var reg 6 , no_of_bytes [5:0] $end
$var reg 1 - page_wrt $end
$var reg 1 . read $end
$var reg 1 / rst $end
$var integer 32 0 i [31:0] $end
$var integer 32 1 j [31:0] $end
$scope module dut $end
$var wire 3 2 a_n [2:0] $end
$var wire 16 3 addr [15:0] $end
$var wire 1 ) clk $end
$var wire 8 4 din [7:0] $end
$var wire 8 5 dout [7:0] $end
$var wire 1 + newd $end
$var wire 6 6 no_of_bytes [5:0] $end
$var wire 1 - page_wrt $end
$var wire 1 . read $end
$var wire 1 / reset $end
$var wire 1 " scl $end
$var wire 1 ! sda $end
$var parameter 32 7 ACK_1 $end
$var parameter 32 8 ACK_2 $end
$var parameter 32 9 ACK_3 $end
$var parameter 32 : ACK_4 $end
$var parameter 32 ; ACK_5 $end
$var parameter 32 < IDLE $end
$var parameter 32 = MASTER_ACK $end
$var parameter 32 > PAGE_WRITE $end
$var parameter 32 ? READ_DATA $end
$var parameter 32 @ START $end
$var parameter 32 A STOP $end
$var parameter 32 B WRITE_ADDR_H $end
$var parameter 32 C WRITE_ADDR_L $end
$var parameter 32 D WRITE_CTRL $end
$var parameter 32 E WRITE_DATA $end
$var parameter 32 F clk_count $end
$var parameter 32 G clk_count4 $end
$var parameter 32 H i2c_freq $end
$var parameter 32 I sys_freq $end
$var reg 1 & ack_err $end
$var reg 4 J bit_count [3:0] $end
$var reg 1 % busy $end
$var reg 8 K data_addr_h [7:0] $end
$var reg 8 L data_addr_l [7:0] $end
$var reg 8 M data_ctrl [7:0] $end
$var reg 8 N data_tx [7:0] $end
$var reg 1 $ done $end
$var reg 2 O pulse [1:0] $end
$var reg 1 P r_ack $end
$var reg 8 Q rx_data [7:0] $end
$var reg 1 R scl_t $end
$var reg 1 S sda_en $end
$var reg 1 T sda_t $end
$var reg 5 U state [4:0] $end
$var integer 32 V count [31:0] $end
$var integer 32 W p_count [31:0] $end
$upscope $end
$upscope $end
$enddefinitions $end
$comment Show the parameter values. $end
$dumpall
b10011000100101101000000000 I
b11000011010100000 H
b110010000 G
b1100100 F
b100 E
b10 D
b1010 C
b1001 B
b1000 A
b1 @
b101 ?
b1110 >
b111 =
b0 <
b1101 ;
b1100 :
b1011 9
b110 8
b11 7
$end
#0
$dumpvars
b0 W
b0 V
bx U
0T
xS
0R
bx Q
xP
b0 O
b0 N
b0 M
bx L
bx K
b0 J
b0 6
bx 5
b0 4
b0 3
b0 2
bx 1
b111111 0
1/
0.
0-
b0 ,
0+
b0 *
0)
b0 (
b0 '
x&
x%
x$
bx #
0"
x!
$end
#5
b0 U
0$
0&
0%
1T
1"
1R
1)
#10
0)
b101 1
#15
1)
#20
0)
#25
1)
#30
0)
#35
1)
#40
0)
#45
1%
b10101010 N
b11001101 L
b10101011 K
b10101010 M
b1 U
b101 ,
b101 6
b10101010 *
b10101010 4
b1010101111001101 (
b1010101111001101 3
1-
b101 '
b101 2
1+
0/
1)
#50
0)
#55
1!
1S
b1 V
1)
#60
0)
#65
b10 V
1)
#70
0)
#75
b11 V
1)
#80
0)
#85
b100 V
1)
#90
0)
#95
b101 V
1)
#100
0)
#105
b110 V
1)
#110
0)
#115
b111 V
1)
#120
0)
#125
b1000 V
1)
#130
0)
#135
b1001 V
1)
#140
0)
#145
b1010 V
1)
#150
0)
#155
b1011 V
1)
#160
0)
#165
b1100 V
1)
#170
0)
#175
b1101 V
1)
#180
0)
#185
b1110 V
1)
#190
0)
#195
b1111 V
1)
#200
0)
#205
b10000 V
1)
#210
0)
#215
b10001 V
1)
#220
0)
#225
b10010 V
1)
#230
0)
#235
b10011 V
1)
#240
0)
#245
b10100 V
1)
#250
0)
#255
b10101 V
1)
#260
0)
#265
b10110 V
1)
#270
0)
#275
b10111 V
1)
#280
0)
#285
b11000 V
1)
#290
0)
#295
b11001 V
1)
#300
0)
#305
b11010 V
1)
#310
0)
#315
b11011 V
1)
#320
0)
#325
b11100 V
1)
#330
0)
#335
b11101 V
1)
#340
0)
#345
b11110 V
1)
#350
0)
#355
b11111 V
1)
#360
0)
#365
b100000 V
1)
#370
0)
#375
b100001 V
1)
#380
0)
#385
b100010 V
1)
#390
0)
#395
b100011 V
1)
#400
0)
#405
b100100 V
1)
#410
0)
#415
b100101 V
1)
#420
0)
#425
b100110 V
1)
#430
0)
#435
b100111 V
1)
#440
0)
#445
b101000 V
1)
#450
0)
#455
b101001 V
1)
#460
0)
#465
b101010 V
1)
#470
0)
#475
b101011 V
1)
#480
0)
#485
b101100 V
1)
#490
0)
#495
b101101 V
1)
#500
0)
#505
b101110 V
1)
#510
0)
#515
b101111 V
1)
#520
0)
#525
b110000 V
1)
#530
0)
#535
b110001 V
1)
#540
0)
#545
b110010 V
1)
#550
0)
#555
b110011 V
1)
#560
0)
#565
b110100 V
1)
#570
0)
#575
b110101 V
1)
#580
0)
#585
b110110 V
1)
#590
0)
#595
b110111 V
1)
#600
0)
#605
b111000 V
1)
#610
0)
#615
b111001 V
1)
#620
0)
#625
b111010 V
1)
#630
0)
#635
b111011 V
1)
#640
0)
#645
b111100 V
1)
#650
0)
#655
b111101 V
1)
#660
0)
#665
b111110 V
1)
#670
0)
#675
b111111 V
1)
#680
0)
#685
b1000000 V
1)
#690
0)
#695
b1000001 V
1)
#700
0)
#705
b1000010 V
1)
#710
0)
#715
b1000011 V
1)
#720
0)
#725
b1000100 V
1)
#730
0)
#735
b1000101 V
1)
#740
0)
#745
b1000110 V
1)
#750
0)
#755
b1000111 V
1)
#760
0)
#765
b1001000 V
1)
#770
0)
#775
b1001001 V
1)
#780
0)
#785
b1001010 V
1)
#790
0)
#795
b1001011 V
1)
#800
0)
#805
b1001100 V
1)
#810
0)
#815
b1001101 V
1)
#820
0)
#825
b1001110 V
1)
#830
0)
#835
b1001111 V
1)
#840
0)
#845
b1010000 V
1)
#850
0)
#855
b1010001 V
1)
#860
0)
#865
b1010010 V
1)
#870
0)
#875
b1010011 V
1)
#880
0)
#885
b1010100 V
1)
#890
0)
#895
b1010101 V
1)
#900
0)
#905
b1010110 V
1)
#910
0)
#915
b1010111 V
1)
#920
0)
#925
b1011000 V
1)
#930
0)
#935
b1011001 V
1)
#940
0)
#945
b1011010 V
1)
#950
0)
#955
b1011011 V
1)
#960
0)
#965
b1011100 V
1)
#970
0)
#975
b1011101 V
1)
#980
0)
#985
b1011110 V
1)
#990
0)
#995
b1011111 V
1)
#1000
0)
#1005
b1100000 V
1)
#1010
0)
#1015
b1100001 V
1)
#1020
0)
#1025
b1100010 V
1)
#1030
0)
#1035
b1100011 V
1)
#1040
0)
#1045
b0 V
b1 O
1)
#1050
0)
#1055
b1 V
1)
#1060
0)
#1065
b10 V
1)
#1070
0)
#1075
b11 V
1)
#1080
0)
#1085
b100 V
1)
#1090
0)
#1095
b101 V
1)
#1100
0)
#1105
b110 V
1)
#1110
0)
#1115
b111 V
1)
#1120
0)
#1125
b1000 V
1)
#1130
0)
#1135
b1001 V
1)
#1140
0)
#1145
b1010 V
1)
#1150
0)
#1155
b1011 V
1)
#1160
0)
#1165
b1100 V
1)
#1170
0)
#1175
b1101 V
1)
#1180
0)
#1185
b1110 V
1)
#1190
0)
#1195
b1111 V
1)
#1200
0)
#1205
b10000 V
1)
#1210
0)
#1215
b10001 V
1)
#1220
0)
#1225
b10010 V
1)
#1230
0)
#1235
b10011 V
1)
#1240
0)
#1245
b10100 V
1)
#1250
0)
#1255
b10101 V
1)
#1260
0)
#1265
b10110 V
1)
#1270
0)
#1275
b10111 V
1)
#1280
0)
#1285
b11000 V
1)
#1290
0)
#1295
b11001 V
1)
#1300
0)
#1305
b11010 V
1)
#1310
0)
#1315
b11011 V
1)
#1320
0)
#1325
b11100 V
1)
#1330
0)
#1335
b11101 V
1)
#1340
0)
#1345
b11110 V
1)
#1350
0)
#1355
b11111 V
1)
#1360
0)
#1365
b100000 V
1)
#1370
0)
#1375
b100001 V
1)
#1380
0)
#1385
b100010 V
1)
#1390
0)
#1395
b100011 V
1)
#1400
0)
#1405
b100100 V
1)
#1410
0)
#1415
b100101 V
1)
#1420
0)
#1425
b100110 V
1)
#1430
0)
#1435
b100111 V
1)
#1440
0)
#1445
b101000 V
1)
#1450
0)
#1455
b101001 V
1)
#1460
0)
#1465
b101010 V
1)
#1470
0)
#1475
b101011 V
1)
#1480
0)
#1485
b101100 V
1)
#1490
0)
#1495
b101101 V
1)
#1500
0)
#1505
b101110 V
1)
#1510
0)
#1515
b101111 V
1)
#1520
0)
#1525
b110000 V
1)
#1530
0)
#1535
b110001 V
1)
#1540
0)
#1545
b110010 V
1)
#1550
0)
#1555
b110011 V
1)
#1560
0)
#1565
b110100 V
1)
#1570
0)
#1575
b110101 V
1)
#1580
0)
#1585
b110110 V
1)
#1590
0)
#1595
b110111 V
1)
#1600
0)
#1605
b111000 V
1)
#1610
0)
#1615
b111001 V
1)
#1620
0)
#1625
b111010 V
1)
#1630
0)
#1635
b111011 V
1)
#1640
0)
#1645
b111100 V
1)
#1650
0)
#1655
b111101 V
1)
#1660
0)
#1665
b111110 V
1)
#1670
0)
#1675
b111111 V
1)
#1680
0)
#1685
b1000000 V
1)
#1690
0)
#1695
b1000001 V
1)
#1700
0)
#1705
b1000010 V
1)
#1710
0)
#1715
b1000011 V
1)
#1720
0)
#1725
b1000100 V
1)
#1730
0)
#1735
b1000101 V
1)
#1740
0)
#1745
b1000110 V
1)
#1750
0)
#1755
b1000111 V
1)
#1760
0)
#1765
b1001000 V
1)
#1770
0)
#1775
b1001001 V
1)
#1780
0)
#1785
b1001010 V
1)
#1790
0)
#1795
b1001011 V
1)
#1800
0)
#1805
b1001100 V
1)
#1810
0)
#1815
b1001101 V
1)
#1820
0)
#1825
b1001110 V
1)
#1830
0)
#1835
b1001111 V
1)
#1840
0)
#1845
b1010000 V
1)
#1850
0)
#1855
b1010001 V
1)
#1860
0)
#1865
b1010010 V
1)
#1870
0)
#1875
b1010011 V
1)
#1880
0)
#1885
b1010100 V
1)
#1890
0)
#1895
b1010101 V
1)
#1900
0)
#1905
b1010110 V
1)
#1910
0)
#1915
b1010111 V
1)
#1920
0)
#1925
b1011000 V
1)
#1930
0)
#1935
b1011001 V
1)
#1940
0)
#1945
b1011010 V
1)
#1950
0)
#1955
b1011011 V
1)
#1960
0)
#1965
b1011100 V
1)
#1970
0)
#1975
b1011101 V
1)
#1980
0)
#1985
b1011110 V
1)
#1990
0)
#1995
b1011111 V
1)
#2000
0)
#2005
b1100000 V
1)
#2010
0)
#2015
b1100001 V
1)
#2020
0)
#2025
b1100010 V
1)
#2030
0)
#2035
b1100011 V
1)
#2040
0)
#2045
b0 V
b10 O
1)
#2050
0)
#2055
b1 V
0!
0T
1)
#2060
0)
#2065
b10 V
1)
#2070
0)
#2075
b11 V
1)
#2080
0)
#2085
b100 V
1)
#2090
0)
#2095
b101 V
1)
#2100
0)
#2105
b110 V
1)
#2110
0)
#2115
b111 V
1)
#2120
0)
#2125
b1000 V
1)
#2130
0)
#2135
b1001 V
1)
#2140
0)
#2145
b1010 V
1)
#2150
0)
#2155
b1011 V
1)
#2160
0)
#2165
b1100 V
1)
#2170
0)
#2175
b1101 V
1)
#2180
0)
#2185
b1110 V
1)
#2190
0)
#2195
b1111 V
1)
#2200
0)
#2205
b10000 V
1)
#2210
0)
#2215
b10001 V
1)
#2220
0)
#2225
b10010 V
1)
#2230
0)
#2235
b10011 V
1)
#2240
0)
#2245
b10100 V
1)
#2250
0)
#2255
b10101 V
1)
#2260
0)
#2265
b10110 V
1)
#2270
0)
#2275
b10111 V
1)
#2280
0)
#2285
b11000 V
1)
#2290
0)
#2295
b11001 V
1)
#2300
0)
#2305
b11010 V
1)
#2310
0)
#2315
b11011 V
1)
#2320
0)
#2325
b11100 V
1)
#2330
0)
#2335
b11101 V
1)
#2340
0)
#2345
b11110 V
1)
#2350
0)
#2355
b11111 V
1)
#2360
0)
#2365
b100000 V
1)
#2370
0)
#2375
b100001 V
1)
#2380
0)
#2385
b100010 V
1)
#2390
0)
#2395
b100011 V
1)
#2400
0)
#2405
b100100 V
1)
#2410
0)
#2415
b100101 V
1)
#2420
0)
#2425
b100110 V
1)
#2430
0)
#2435
b100111 V
1)
#2440
0)
#2445
b101000 V
1)
#2450
0)
#2455
b101001 V
1)
#2460
0)
#2465
b101010 V
1)
#2470
0)
#2475
b101011 V
1)
#2480
0)
#2485
b101100 V
1)
#2490
0)
#2495
b101101 V
1)
#2500
0)
#2505
b101110 V
1)
#2510
0)
#2515
b101111 V
1)
#2520
0)
#2525
b110000 V
1)
#2530
0)
#2535
b110001 V
1)
#2540
0)
#2545
b110010 V
1)
#2550
0)
#2555
b110011 V
1)
#2560
0)
#2565
b110100 V
1)
#2570
0)
#2575
b110101 V
1)
#2580
0)
#2585
b110110 V
1)
#2590
0)
#2595
b110111 V
1)
#2600
0)
#2605
b111000 V
1)
#2610
0)
#2615
b111001 V
1)
#2620
0)
#2625
b111010 V
1)
#2630
0)
#2635
b111011 V
1)
#2640
0)
#2645
b111100 V
1)
#2650
0)
#2655
b111101 V
1)
#2660
0)
#2665
b111110 V
1)
#2670
0)
#2675
b111111 V
1)
#2680
0)
#2685
b1000000 V
1)
#2690
0)
#2695
b1000001 V
1)
#2700
0)
#2705
b1000010 V
1)
#2710
0)
#2715
b1000011 V
1)
#2720
0)
#2725
b1000100 V
1)
#2730
0)
#2735
b1000101 V
1)
#2740
0)
#2745
b1000110 V
1)
#2750
0)
#2755
b1000111 V
1)
#2760
0)
#2765
b1001000 V
1)
#2770
0)
#2775
b1001001 V
1)
#2780
0)
#2785
b1001010 V
1)
#2790
0)
#2795
b1001011 V
1)
#2800
0)
#2805
b1001100 V
1)
#2810
0)
#2815
b1001101 V
1)
#2820
0)
#2825
b1001110 V
1)
#2830
0)
#2835
b1001111 V
1)
#2840
0)
#2845
b1010000 V
1)
#2850
0)
#2855
b1010001 V
1)
#2860
0)
#2865
b1010010 V
1)
#2870
0)
#2875
b1010011 V
1)
#2880
0)
#2885
b1010100 V
1)
#2890
0)
#2895
b1010101 V
1)
#2900
0)
#2905
b1010110 V
1)
#2910
0)
#2915
b1010111 V
1)
#2920
0)
#2925
b1011000 V
1)
#2930
0)
#2935
b1011001 V
1)
#2940
0)
#2945
b1011010 V
1)
#2950
0)
#2955
b1011011 V
1)
#2960
0)
#2965
b1011100 V
1)
#2970
0)
#2975
b1011101 V
1)
#2980
0)
#2985
b1011110 V
1)
#2990
0)
#2995
b1011111 V
1)
#3000
0)
#3005
b1100000 V
1)
#3010
0)
#3015
b1100001 V
1)
#3020
0)
#3025
b1100010 V
1)
#3030
0)
#3035
b1100011 V
1)
#3040
0)
#3045
b0 V
b11 O
1)
#3050
0)
#3055
b1 V
1)
#3060
0)
#3065
b10 V
1)
#3070
0)
#3075
b11 V
1)
#3080
0)
#3085
b100 V
1)
#3090
0)
#3095
b101 V
1)
#3100
0)
#3105
b110 V
1)
#3110
0)
#3115
b111 V
1)
#3120
0)
#3125
b1000 V
1)
#3130
0)
#3135
b1001 V
1)
#3140
0)
#3145
b1010 V
1)
#3150
0)
#3155
b1011 V
1)
#3160
0)
#3165
b1100 V
1)
#3170
0)
#3175
b1101 V
1)
#3180
0)
#3185
b1110 V
1)
#3190
0)
#3195
b1111 V
1)
#3200
0)
#3205
b10000 V
1)
#3210
0)
#3215
b10001 V
1)
#3220
0)
#3225
b10010 V
1)
#3230
0)
#3235
b10011 V
1)
#3240
0)
#3245
b10100 V
1)
#3250
0)
#3255
b10101 V
1)
#3260
0)
#3265
b10110 V
1)
#3270
0)
#3275
b10111 V
1)
#3280
0)
#3285
b11000 V
1)
#3290
0)
#3295
b11001 V
1)
#3300
0)
#3305
b11010 V
1)
#3310
0)
#3315
b11011 V
1)
#3320
0)
#3325
b11100 V
1)
#3330
0)
#3335
b11101 V
1)
#3340
0)
#3345
b11110 V
1)
